rtl/pipeline/modules/multiplier/mult_half_precision.v
//-----------------------------------------------------
// Design Name : multhalfprecision
// File Name   : multhalfprecision.v
// Coder     : Badilla
//-----------------------------------------------------
module multhalfprecision(
output reg [15:0]	o_Product,	//Output of the mult
output reg 			o_Exception,
input wire [15:0]   i_Factor1,	//Input Factor 1
input wire [15:0]   i_Factor2	//Input Factor 2
);
/*	initial
	begin
		$dumpfile ("signals_multiplier.vcd");
		$dumpvars;
	end
*/
//------------Internal Variables--------
wire[21:0]	w_Mantissa_Product; 
wire[4:0]	w_Sum_Exps;
wire		w_AND_MSB_Exps;
wire 		w_NOR_MSB_Exps;

//Assignments:
	assign w_Mantissa_Product[21:0] = {1'b1,i_Factor1[9:0]}*{1'b1,i_Factor2[9:0]};
	assign w_Sum_Exps[4:0] = i_Factor1[14:10] + i_Factor2[14:10];
	assign w_AND_MSB_Exps = i_Factor1[14] && i_Factor2[14];
	assign w_NOR_MSB_Exps = i_Factor1[14] ~||  i_Factor2[14];

//Code Starts Here
	always @(*) begin
		if (i_Factor1[14:0] == 15'b0 || i_Factor2[14:0] == 15'b0) begin //Special case, some is zero.
		o_Product[15:0] = 16'b0;
		o_Exception = 1'b0;			
		end
		else if ( (w_AND_MSB_Exps == 1'b1 && w_Sum_Exps[4:0] >= 5'd14 )) begin //Positive exponents, no more than 14 the sum, else overflow.
		o_Product[15] <= i_Factor1[15] ^ i_Factor2[15];
			if(w_Sum_Exps[4:0] == 5'd14) begin//Sum of exponets equal zero, depends of the result mantissa overflow or not.
			o_Product[14:0] = (w_Mantissa_Product[21]) ? 15'b111111111111111 : {5'b11111,w_Mantissa_Product[19:10]};
			o_Exception = (w_Mantissa_Product[21]) ? 1'b1 : 1'b0;
			end
			else begin
			o_Product[14:0] = 15'b111111111111111;
			o_Exception = 1'b1;			
			end
		end
		else if((w_NOR_MSB_Exps == 1'b1) && (w_Sum_Exps[4:0] < 5'd15)) begin //Negative exponents, no less than 15 the sum, else underflow.
		o_Product[15] = i_Factor1[15] ^ i_Factor2[15];
		o_Product[14:0] = 15'd0;
		o_Exception = 1'b1;			
		end
		else begin //General case.
		o_Product[15] = i_Factor1[15] ^ i_Factor2[15];
			if ( (i_Factor1[14:10] == 5'b11111 && i_Factor2[14:10]==5'b01111) || (i_Factor2[14:10]==5'b11111 && i_Factor1[14:10] == 5'b01111) ) begin
				o_Product[14:0] = (w_Mantissa_Product[21]) ? 15'b111111111111111 : {5'b11111,w_Mantissa_Product[19:10]};
				o_Exception = (w_Mantissa_Product[21]) ? 1'b1 : 1'b0; 
				end
			else begin
				o_Product[14:10] = (w_Mantissa_Product[21]) ? i_Factor1[14:10] + i_Factor2[14:10] - 5'd14 : i_Factor1[14:10] + i_Factor2[14:10] - 5'd15; // E_1 - 15 + E_2 - 15 + 1 + 15
				o_Product[9:0]   = (w_Mantissa_Product[21]) ? w_Mantissa_Product[20:11] : w_Mantissa_Product[19:10];
				o_Exception = 1'b0;	
			end
		end
	end
endmodule

testbench/pipeline/modules/multiplier/testmultiplier.v
`include "../../../../rtl/pipeline/modules/multiplier/mult_half_precision.v"
module testmultiplier(
	output reg [15:0] testintnum1,
	output reg [15:0] testintnum2,
	input  wire[15:0] resultmultiplier,
	input  wire 	  exception
);
real exp1, exp2, S1, S2, float1, float2;
real result, expresult, Sresult, porcentaje;
reg[3:0] i=0;
initial begin
		$display("In1:\t\tIn2:\t\tResult:\t\tError:\t\tException:");
	repeat(25) begin
#3 float1=0; float2=0; result=0; exp1=0; exp2=0; S1=0; S2=0; expresult=0; Sresult=0; porcentaje=0;
		testintnum1 = $random % 32768;
		testintnum2 = $random % 32768;
		S1 = (-1.0)**(testintnum1[15]);
		S2 = (-1.0)**(testintnum2[15]);
		exp1 = testintnum1[14:10]-15.0;
		exp2 = testintnum2[14:10]-15.0;
		for(i=1; i<10; i=i+1) begin
		if(testintnum1[i]==1'b1)
			float1 = float1 + 2.0**(-1.0*((10.0-i)));
		if(testintnum2[i]==1'b1)
			float2 = float2 + 2.0**(-1.0*((10.0-i)));
		end
		float1 = (S1)*(2.0**(exp1))*(1.0+float1);
		float2 = (S2)*(2.0**(exp2))*(1.0+float2);
#1
		Sresult = (-1.0)**(resultmultiplier[15]);
		expresult = resultmultiplier[14:10]-15.0;
		for(i=1; i<10; i=i+1) begin
		if(resultmultiplier[i]==1'b1)
			result = result + 2.0**(-1.0*((10.0-i)));
		end
		result = (Sresult)*(2.0**(expresult))*(1.0+result);
		porcentaje = (float1*float2-result)/(float1*float2)*100;
		$display("%f\t",float1, "%f\t", float2,"%f\t", result, "%f %%\t",porcentaje, "%b",exception);
	end
		#5 $finish;
	end
multhalfprecision c1 (
.i_Factor1(testintnum1),  
.i_Factor2(testintnum2),
.o_Product(resultmultiplier),
.o_Exception(exception)
);
endmodule

testbench/pipeline/modules/multiplier/signals_multiplier.vcd
$date
	Mon Jun 12 22:20:59 2017
$end
$version
	Icarus Verilog
$end
$timescale
	1s
$end
$scope module testmultiplier $end
$var wire 1 ! exception $end
$var wire 16 " resultmultiplier [15:0] $end
$var reg 4 # i [3:0] $end
$var reg 16 $ testintnum1 [15:0] $end
$var reg 16 % testintnum2 [15:0] $end
$var real 1 & S1 $end
$var real 1 ' S2 $end
$var real 1 ( Sresult $end
$var real 1 ) exp1 $end
$var real 1 * exp2 $end
$var real 1 + expresult $end
$var real 1 , float1 $end
$var real 1 - float2 $end
$var real 1 . porcentaje $end
$var real 1 / result $end
$scope module c1 $end
$var wire 16 0 i_Factor1 [15:0] $end
$var wire 16 1 i_Factor2 [15:0] $end
$var wire 1 2 w_AND_MSB_Exps $end
$var wire 22 3 w_Mantissa_Product [21:0] $end
$var wire 1 4 w_NOR_MSB_Exps $end
$var wire 5 5 w_Sum_Exps [4:0] $end
$var reg 1 6 o_Exception $end
$var reg 16 7 o_Product [15:0] $end
$upscope $end
$upscope $end
$enddefinitions $end
#0
$dumpvars
bx 7
06
bx 5
x4
bx 3
x2
bx 1
bx 0
r0 /
r0 .
r0 -
r0 ,
r0 +
r0 *
r0 )
r0 (
r0 '
r0 &
bx %
bx $
b0 #
bx "
0!
$end
#3
04
02
b1000010110111100100100 3
b100 5
b1101100000101101 7
b1101100000101101 "
r-416 -
r0.3212890625 ,
b1010 #
r8 *
r-2 )
r-1 '
r1 &
b1101111010000001 %
b1101111010000001 1
b11010100100100 $
b11010100100100 0
#4
r0.1169043722235212 .
r-133.5 /
b1010 #
r7 +
r-1 (
#7
12
b111000011010001 7
b111000011010001 "
b1001101000101101111011 3
b1010 5
b1010 #
b1101011001100011 %
b1101011001100011 1
b1101011000001001 $
b1101011000001001 0
r0 .
r0 (
r0 +
r-1 '
r-1 &
r6 *
r6 )
r0 /
r-102.125 -
r-96.5 ,
#8
r-0.009512877264857529 .
r9856 /
b1010 #
r13 +
r1 (
#11
02
06
0!
b101100011100100 "
b101100011100100 7
b1001110010001100101001 3
b100 5
b1010 #
b1100110001101 %
b1100110001101 1
b111101100001101 $
b111101100001101 0
r0 .
r0 (
r0 +
r1 '
r1 &
r-9 *
r15 )
r0 /
r0.00270843505859375 -
r57728 ,
#12
r-0.09431310702351582 .
r156.5 /
b1010 #
r7 +
r1 (
#15
b1101010101011 "
b1101010101011 7
b110101010110100011010 3
b10101 5
b1010 #
b1101001000010010 %
b1101001000010010 1
b1000010001100101 $
b1000010001100101 0
r0 .
r0 (
r0 +
r-1 '
r-1 &
r5 *
r-14 )
r0 /
r-48.5625 -
r-6.699562072753906e-05 ,
#16
r-0.01419823483880423 .
r0.003253936767578125 /
b1010 #
r-9 +
r1 (
#19
12
b111010001101100 "
b111010001101100 7
b1000110110000000001101 3
b1011 5
b1010 #
b100110100001101 %
b100110100001101 1
b110001100000001 $
b110001100000001 0
r0 .
r0 (
r0 +
r1 '
r1 &
r4 *
r9 )
r0 /
r20.1875 -
r896 ,
#20
r-0.1326846528084918 .
r18112 /
b1010 #
r14 +
r1 (
#23
16
1!
b111111111111111 "
b111111111111111 7
b111001001101100011110 3
b1111 5
b1010 #
b100110100111101 %
b100110100111101 1
b111000101110110 $
b111000101110110 0
r0 .
r0 (
r0 +
r1 '
r1 &
r4 *
r13 )
r0 /
r20.9375 -
r11184 ,
#24
r44.08045608865543 .
r130944 /
b1010 #
r16 +
r1 (
#27
16
1!
b111111111111111 "
b111111111111111 7
b1110111101000010011100 3
b10010 5
b1010 #
b111011110001100 %
b111011110001100 1
b101011111101101 $
b101011111101101 0
r0 .
r0 (
r0 +
r1 '
r1 &
r14 *
r6 )
r0 /
r30912 -
r126.75 ,
#28
r96.65796856432308 .
r130944 /
b1010 #
r16 +
r1 (
#31
06
0!
02
b1101001100100000 7
b1101001100100000 "
b111001000001010010110 3
b11 5
b1010 #
b1010010011000110 %
b1010010011000110 1
b110100111111001 $
b110100111111001 0
r0 .
r0 (
r0 +
r-1 '
r1 &
r-6 *
r11 )
r0 /
r-0.018646240234375 -
r3056 ,
#32
r-0.02999117402592951 .
r-57 /
b1010 #
r5 +
r-1 (
#35
b1101111110010 7
b1101111110010 "
b111111100100011010010 3
b10101 5
b1010 #
b1101001010101010 %
b1101001010101010 1
b1000010011000101 $
b1000010011000101 0
r0 .
r0 (
r0 +
r-1 '
r-1 &
r5 *
r-14 )
r0 /
r-53.3125 -
r-7.271766662597656e-05 ,
#36
r-0.07187746237964368 .
r0.003879547119140625 /
b1010 #
r-9 +
r1 (
#39
16
1!
12
b1111111111111111 7
b1111111111111111 "
b1100110000100101110011 3
b11001 5
b1010 #
b1111001001110111 %
b1111001001110111 1
b111011111100101 $
b111011111100101 0
r0 .
r0 (
r0 +
r-1 '
r1 &
r13 *
r14 )
r0 /
r-13232 -
r32320 ,
#40
r99.96938115818837 .
r-130944 /
b1010 #
r16 +
r-1 (
#43
06
0!
b1111010110111100 "
b1111010110111100 7
b1011011110001000001110 3
b1011 5
b1010 #
b101101110001111 %
b101101110001111 1
b1101011000010010 $
b1101011000010010 0
r0 .
r0 (
r0 +
r1 '
r-1 &
r7 *
r6 )
r0 /
r241.75 -
r-97.125 ,
#44
r-0.03420468777242303 .
r-23488 /
b1010 #
r14 +
r-1 (
#47
02
06
0!
b1100010100001110 "
b1100010100001110 7
b1010000111010010111100 3
b11111 5
b1010 #
b1001011011001110 %
b1001011011001110 1
b110100111110010 $
b110100111110010 0
r0 .
r0 (
r0 +
r-1 '
r1 &
r-10 *
r11 )
r0 /
r-0.001661300659179688 -
r3044 ,
#48
r0.0457130098018952 .
r-5.0546875 /
b1010 #
r2 +
r-1 (
#51
16
1!
12
b111111111111111 7
b111111111111111 "
b1011101100000010001000 3
b10001 5
b1010 #
b1100111011000101 %
b1100111011000101 1
b1111101011101000 $
b1111101011101000 0
r0 .
r0 (
r0 +
r-1 '
r-1 &
r4 *
r15 )
r0 /
r-27.0625 -
r-56576 ,
#52
r91.44765029834994 .
r130944 /
b1010 #
r16 +
r1 (
#55
02
06
0!
b1011011001011001 7
b1011011001011001 "
b110010110010011101100 3
b11100 5
b1010 #
b1010100010111101 %
b1010100010111101 1
b100100101011100 $
b100100101011100 0
r0 .
r0 (
r0 +
r-1 '
r1 &
r-5 *
r3 )
r0 /
r-0.0369873046875 -
r10.71875 ,
#56
r-0.00673536741429245 .
r-0.396484375 /
b1010 #
r-2 +
r-1 (
#59
b100001010101100 7
b100001010101100 "
b110101011001111000001 3
b11111 5
b1010 #
b1010011001100101 %
b1010011001100101 1
b1101100000101101 $
b1101100000101101 0
r0 .
r0 (
r0 +
r-1 '
r-1 &
r-6 *
r7 )
r0 /
r-0.02496337890625 -
r-133.5 ,
#60
r-0.09981410767103467 .
r3.3359375 /
b1010 #
r1 +
r1 (
#63
b1010110110011110 7
b1010110110011110 "
b1011001111010011011110 3
b11001 5
b1010 #
b11100001010 %
b11100001010 1
b1110001001100011 $
b1110001001100011 0
r0 .
r0 (
r0 +
r1 '
r-1 &
r-14 *
r9 )
r0 /
r0.0001074075698852539 -
r-817 ,
#64
r-0.01888286780498209 .
r-0.0877685546875 /
b1010 #
r-4 +
r-1 (
#67
14
b1000100000101010 "
b1000100000101010 7
b1000010101000000000000 3
b10000 5
b1010 #
b10000100100000 %
b10000100100000 1
b1010001010000000 $
b1010001010000000 0
r0 .
r0 (
r0 +
r1 '
r-1 &
r-7 *
r-7 )
r0 /
r0.010009765625 -
r-0.0126953125 ,
#68
r-0 .
r-0.0001270771026611328 /
b1010 #
r-13 +
r-1 (
#71
04
06
0!
12
b1101011010001000 "
b1101011010001000 7
b110100010000101000010 3
b100 5
b1010 #
b1100110010011101 %
b1100110010011101 1
b100010110101010 $
b100010110101010 0
r0 .
r0 (
r0 +
r-1 '
r1 &
r4 *
r2 )
r0 /
r-18.4375 -
r5.6640625 ,
#72
r-0.06592635885447107 .
r-104.5 /
b1010 #
r6 +
r-1 (
#75
14
02
b11101010110101 7
b11101010110101 "
b110101101010100100010 3
b11101 5
b1010 #
b1011100000010011 %
b1011100000010011 1
b1011111010010110 $
b1011111010010110 0
r0 .
r0 (
r0 +
r-1 '
r-1 &
r-1 *
r0 )
r0 /
r-0.5087890625 -
r-1.646484375 ,
#76
r-0.02117471875192109 .
r0.837890625 /
b1010 #
r-1 +
r1 (
#79
04
06
0!
b101001001100111 "
b101001001100111 7
b110011001111000110111 3
b11 5
b1010 #
r-1 )
b1101011001010011 %
b1101011001010011 1
b1011100000001101 $
b1011100000001101 0
r0 .
r0 (
r0 +
r-1 '
r-1 &
r6 *
r0 /
r-101.125 -
r-0.505859375 ,
#80
r-0.06347509437744296 .
r51.1875 /
b1010 #
r5 +
r1 (
#83
b1100110010100000 7
b1100110010100000 "
b1001010000010000000111 3
b1 5
b1010 #
b1010101011010101 %
b1010101011010101 1
b101110101101011 $
b101110101101011 0
r0 .
r0 (
r0 +
r-1 '
r1 &
r-5 *
r8 )
r0 /
r-0.0533447265625 -
r346.5 ,
#84
r-0.086844251603977 .
r-18.5 /
b1010 #
r4 +
r-1 (
#87
b100110100000100 7
b100110100000100 "
b1010000010000101011100 3
b1 5
b1010 #
b1011111010101110 %
b1011111010101110 1
b1100101000000010 $
b1100101000000010 0
r0 .
r0 (
r0 +
r-1 '
r-1 &
r0 *
r3 )
r0 /
r-1.669921875 -
r-12.015625 ,
#88
r0.01323203978737481 .
r20.0625 /
b1010 #
r4 +
r1 (
#91
16
1!
12
b1111111111111111 7
b1111111111111111 "
b1000101101000001110011 3
b10110 5
b1010 #
r13 *
b1111001011001111 %
b1111001011001111 1
b110100100011101 $
b110100100011101 0
r0 .
r0 (
r0 +
r-1 '
r1 &
r11 )
r0 /
r-13936 -
r2616 ,
#92
r99.64082200149569 .
r-130944 /
b1010 #
r16 +
r-1 (
#95
06
0!
b111001001111000 7
b111001001111000 "
b110011110001001011110 3
b1011 5
b1010 #
b110010100001010 %
b110010100001010 1
b100100100100011 $
b100100100100011 0
r0 .
r0 (
r0 +
r1 '
r1 &
r10 *
r3 )
r0 /
r1290 -
r10.265625 ,
#96
r-0.04035255389189763 .
r13248 /
b1010 #
r13 +
r1 (
#99
02
06
0!
b1101100101111 "
b1101100101111 7
b111001011111101011000 3
b10101 5
b1010 #
b1100110000111100 %
b1100110000111100 1
b1000101011001010 $
b1000101011001010 0
r0 .
r0 (
r0 +
r-1 '
r-1 &
r4 *
r-13 )
r0 /
r-16.9375 -
r-0.0002071857452392578 ,
#100
r0.09978810950364971 .
r0.003505706787109375 /
b1010 #
r-9 +
r1 (
